mp_repl/__init__.py
mp_repl/config.py
mp_repl/connection.py
mp_repl/main.py
mp_repl/repl.py
mp_repl/commands/__init__.py
mp_repl/proxy/__init__.py
mp_repl/proxy/server.py
mp_repl/smgr/__init__.py
mp_repl/smgr/client.py
mp_repl/smgr/helper.py
mp_repl-0.1.45.dist-info/METADATA
mp_repl-0.1.45.dist-info/WHEEL
mp_repl-0.1.45.dist-info/entry_points.txt
mp_repl-0.1.45.dist-info/top_level.txt
mp_repl-0.1.45.dist-info/RECORD
