Metadata-Version: 2.4
Name: mp-repl
Version: 0.1.45
Summary: Playwright 交互式调试工具
License: MIT
Classifier: Development Status :: 3 - Alpha
Classifier: Environment :: Console
Classifier: Intended Audience :: Developers
Classifier: License :: OSI Approved :: MIT License
Classifier: Programming Language :: Python :: 3.10
Classifier: Programming Language :: Python :: 3.11
Classifier: Programming Language :: Python :: 3.12
Requires-Python: >=3.10
Requires-Dist: playwright>=1.40.0
Requires-Dist: prompt_toolkit>=3.0.0
Requires-Dist: httpx>=0.25.0
Provides-Extra: dev
Requires-Dist: pytest; extra == "dev"
Requires-Dist: pytest-asyncio; extra == "dev"
